README.md
setup.py
guard_test.egg-info/PKG-INFO
guard_test.egg-info/SOURCES.txt
guard_test.egg-info/dependency_links.txt
guard_test.egg-info/entry_points.txt
guard_test.egg-info/top_level.txt
guardtest/__init__.py
guardtest/test.py
guardtest/cli/__init__.py
guardtest/cli/entry_points.py