Metadata-Version: 1.0
Name: guard-test
Version: 1.2
Summary: a androguard test
Home-page: UNKNOWN
Author: hy
Author-email: UNKNOWN
License: UNKNOWN
Platform: UNKNOWN
